{
    "os": "Linux-5.14.0-362.18.1.el9_3.x86_64-x86_64-with-glibc2.34",
    "python": "3.9.18",
    "heartbeatAt": "2024-03-04T03:17:05.906856",
    "startedAt": "2024-03-04T03:17:04.198147",
    "docker": null,
    "cuda": null,
    "args": [],
    "state": "running",
    "program": "/users/eleves-b/2021/mathilde.cros/Bachelor-Thesis-Alzheimers-HGNN/GAT.py",
    "codePathLocal": "GAT.py",
    "codePath": "GAT.py",
    "git": {
        "remote": "git@github.com:mathilde-cros/Bachelor-Thesis-Alzheimers-HGNN.git",
        "commit": "cbefd83920849fd8c67ce088d31af7b8c99e1037"
    },
    "email": null,
    "root": "/users/eleves-b/2021/mathilde.cros/Bachelor-Thesis-Alzheimers-HGNN",
    "host": "ferrari.polytechnique.fr",
    "username": "mathilde.cros",
    "executable": "/usr/bin/python",
    "cpu_count": 6,
    "cpu_count_logical": 12,
    "cpu_freq": {
        "current": 4409.676916666666,
        "min": 800.0,
        "max": 4800.0
    },
    "cpu_freq_per_core": [
        {
            "current": 4407.985,
            "min": 800.0,
            "max": 4800.0
        },
        {
            "current": 4408.202,
            "min": 800.0,
            "max": 4800.0
        },
        {
            "current": 4408.326,
            "min": 800.0,
            "max": 4800.0
        },
        {
            "current": 4409.035,
            "min": 800.0,
            "max": 4800.0
        },
        {
            "current": 4409.165,
            "min": 800.0,
            "max": 4800.0
        },
        {
            "current": 4409.682,
            "min": 800.0,
            "max": 4800.0
        },
        {
            "current": 4409.796,
            "min": 800.0,
            "max": 4800.0
        },
        {
            "current": 4410.315,
            "min": 800.0,
            "max": 4800.0
        },
        {
            "current": 4410.425,
            "min": 800.0,
            "max": 4800.0
        },
        {
            "current": 4410.846,
            "min": 800.0,
            "max": 4800.0
        },
        {
            "current": 4410.977,
            "min": 800.0,
            "max": 4800.0
        },
        {
            "current": 4411.369,
            "min": 800.0,
            "max": 4800.0
        }
    ],
    "disk": {
        "/": {
            "total": 3.990234375,
            "used": 0.9619674682617188
        }
    },
    "gpu": "Quadro P2200",
    "gpu_count": 1,
    "gpu_devices": [
        {
            "name": "Quadro P2200",
            "memory_total": 5368709120
        }
    ],
    "memory": {
        "total": 62.366241455078125
    }
}
